xpedition_manager/__init__.py
xpedition_manager/manager.py
xpedition_manager-0.3.dist-info/METADATA
xpedition_manager-0.3.dist-info/WHEEL
xpedition_manager-0.3.dist-info/top_level.txt
xpedition_manager-0.3.dist-info/RECORD
